{
  "configVersion": 1,
  "timestamp": 1660798550060,
  "index": "/index.html",
  "assetGroups": [
    {
      "name": "app",
      "installMode": "prefetch",
      "updateMode": "prefetch",
      "cacheQueryOptions": {
        "ignoreVary": true
      },
      "urls": [
        "/254.0678bf3a27cac68c.js",
        "/574.c0feb36bea3139c5.js",
        "/682.88d9b6b23c2ac94b.js",
        "/main.46c31a315e0102d0.js",
        "/polyfills.578ac00f2cd1f8d5.js",
        "/runtime.468656ec8965f608.js",
        "/scripts.62e0ce834e1ee835.js",
        "/styles.d9d6befba0769f4a.css"
      ],
      "patterns": []
    },
    {
      "name": "assets",
      "installMode": "lazy",
      "updateMode": "prefetch",
      "cacheQueryOptions": {
        "ignoreVary": true
      },
      "urls": [
        "/favicon.png"
      ],
      "patterns": []
    }
  ],
  "dataGroups": [],
  "hashTable": {
    "/254.0678bf3a27cac68c.js": "8bc153b8a9072f9cbe5a2dc56acdf255d6a70f92",
    "/574.c0feb36bea3139c5.js": "43bba3e5179e87f8d3b4de21456d6919435b4a04",
    "/682.88d9b6b23c2ac94b.js": "43d12a81d248ab03b911e2f2d45aa3ba3897a638",
    "/favicon.png": "ceed91f95e7fe8adc5fcb00943ed3ca2388b1bfd",
    "/main.46c31a315e0102d0.js": "87f58983b9082d2b7d85b37bf67c044aff253e0d",
    "/polyfills.578ac00f2cd1f8d5.js": "6f9bb5d237a6d3e83417d3b3ffa151776fdf7fa5",
    "/runtime.468656ec8965f608.js": "27a16020262fcdc26bf406b0fb146e20b240a70c",
    "/scripts.62e0ce834e1ee835.js": "c6aafd85011e3f4a7f7bffea3102910388ae63b4",
    "/styles.d9d6befba0769f4a.css": "21d0a7750e76c550bc34b79476fccd8dedc097e6"
  },
  "navigationUrls": [
    {
      "positive": true,
      "regex": "^\\/.*$"
    },
    {
      "positive": false,
      "regex": "^\\/(?:.+\\/)?[^/]*\\.[^/]*$"
    },
    {
      "positive": false,
      "regex": "^\\/(?:.+\\/)?[^/]*__[^/]*$"
    },
    {
      "positive": false,
      "regex": "^\\/(?:.+\\/)?[^/]*__[^/]*\\/.*$"
    }
  ],
  "navigationRequestStrategy": "performance"
}